karabo/__init__.py
karabo/_version.py
karabo/version.py
karabo/common/__init__.py
karabo/common/alarm_conditions.py
karabo/common/api.py
karabo/common/const.py
karabo/common/decorators.py
karabo/common/display_types.py
karabo/common/enums.py
karabo/common/module.py
karabo/common/sanity_check.py
karabo/common/savable.py
karabo/common/services.py
karabo/common/states.py
karabo/common/utils.py
karabo/common/packaging/__init__.py
karabo/common/packaging/utils.py
karabo/common/packaging/tests/__init__.py
karabo/common/packaging/tests/test_utils.py
karabo/common/project/__init__.py
karabo/common/project/api.py
karabo/common/project/bases.py
karabo/common/project/cache.py
karabo/common/project/const.py
karabo/common/project/device.py
karabo/common/project/device_config.py
karabo/common/project/lazy.py
karabo/common/project/macro.py
karabo/common/project/model.py
karabo/common/project/server.py
karabo/common/project/utils.py
karabo/common/project/tests/__init__.py
karabo/common/project/tests/test_base.py
karabo/common/project/tests/test_cache.py
karabo/common/project/tests/test_device.py
karabo/common/project/tests/test_macro.py
karabo/common/project/tests/test_model.py
karabo/common/project/tests/test_server.py
karabo/common/project/tests/test_utils.py
karabo/common/scenemodel/__init__.py
karabo/common/scenemodel/api.py
karabo/common/scenemodel/bases.py
karabo/common/scenemodel/const.py
karabo/common/scenemodel/exceptions.py
karabo/common/scenemodel/generic_scenes.py
karabo/common/scenemodel/io_utils.py
karabo/common/scenemodel/layouts.py
karabo/common/scenemodel/model.py
karabo/common/scenemodel/modelio.py
karabo/common/scenemodel/registry.py
karabo/common/scenemodel/shapes.py
karabo/common/scenemodel/tests/__init__.py
karabo/common/scenemodel/tests/test_data_model_structure.py
karabo/common/scenemodel/tests/test_graph_images.py
karabo/common/scenemodel/tests/test_graph_plots.py
karabo/common/scenemodel/tests/test_io.py
karabo/common/scenemodel/tests/test_registry.py
karabo_native-3.0.8.dist-info/licenses/LICENSE.md
karabo_native-3.0.8.dist-info/METADATA
karabo_native-3.0.8.dist-info/WHEEL
karabo_native-3.0.8.dist-info/top_level.txt
karabo_native-3.0.8.dist-info/RECORD
