Metadata-Version: 2.4
Name: karabo.native
Version: 3.0.8
Summary: Karabo's native data Python types and models
Author-email: European XFEL GmbH <opensource@xfel.eu>
Maintainer-email: "S. Hauf" <steffen.hauf@xfel.eu>, "D. Goeries" <dennis.goeries@xfel.eu>
License-Expression: MPL-2.0
Project-URL: Homepage, https://github.com/European-XFEL/Karabo
Project-URL: Bug Reports, https://github.com/European-XFEL/Karabo/issues
Project-URL: Source, https://github.com/European-XFEL/Karabo
Keywords: Karabo,SCADA,async,control system
Classifier: Development Status :: 5 - Production/Stable
Classifier: Intended Audience :: Developers
Classifier: Intended Audience :: Science/Research
Requires-Python: >=3.12
License-File: LICENSE.md
Requires-Dist: aiomysql==0.2.0
Requires-Dist: aiosqlite==0.21.0
Requires-Dist: lxml==6.0.2
Requires-Dist: numpy==2.1.3
Requires-Dist: pint>=0.24.4
Requires-Dist: pytest==8.3.3
Requires-Dist: python_dateutil==2.9.0.post0
Requires-Dist: tabulate==0.9.0
Requires-Dist: traits==6.4.3
Dynamic: license-file
